cdtapi/API.py
cdtapi/DevPIAPI.py
cdtapi/DmsAPI.py
cdtapi/DmsGetverAPI.py
cdtapi/ForemanAPI.py
cdtapi/JenkinsAPI.py
cdtapi/NexusAPI.py
cdtapi/TestServer.py
cdtapi/__init__.py
cdtapi/tests/__init__.py
cdtapi/tests/test_API.py
cdtapi/tests/test_ArtifactoryAPI.py
cdtapi/tests/test_DevPIAPI.py
cdtapi/tests/test_DmsAPI.py
cdtapi/tests/test_DmsGetverAPI.py
cdtapi/tests/test_ForemanAPI.py
cdtapi/tests/test_JenkinsAPI.py
cdtapi/tests/test_NexusAPI.py
cdtapi/tests/test_NexusAPI_helpers.py
cdtapi/tests/test_nexus.py
cdtapi/tests/mocks/NexusAPILsMock.py
cdtapi/tests/mocks/__init__.py
cdtapi-3.8.1.20230329065822.data/scripts/nexus.py
cdtapi-3.8.1.20230329065822.dist-info/LICENSE
cdtapi-3.8.1.20230329065822.dist-info/METADATA
cdtapi-3.8.1.20230329065822.dist-info/WHEEL
cdtapi-3.8.1.20230329065822.dist-info/top_level.txt
cdtapi-3.8.1.20230329065822.dist-info/RECORD
