Metadata-Version: 2.1
Name: cdtapi
Version: 3.8.1.20230329065822
Summary: Custom Development python API libraries
Home-page: UNKNOWN
Author: UNKNOWN
Author-email: UNKNOWN
License: Apache2.0
Platform: UNKNOWN
Requires-Dist: requests
Requires-Dist: mock
Requires-Dist: enum
